sdcard_lib/__init__.py
sdcard_lib/sdcard.py
sdcard_lib-0.0.1.dist-info/METADATA
sdcard_lib-0.0.1.dist-info/WHEEL
sdcard_lib-0.0.1.dist-info/top_level.txt
sdcard_lib-0.0.1.dist-info/RECORD
