Metadata-Version: 2.1
Name: sdcard-lib
Version: 0.0.1
Summary: A library for controlling SD cards with ESP32 compatibility, designed for easy installation in Thonny.
Author: Nobody
Author-email: name@email.com
License: License
